enrichr/__init__.py
enrichr/config.py
enrichr/datatypes.py
enrichr/dispatch.py
enrichr/exceptions.py
enrichr/plugin.py
enrichr/plugins/__init__.py
enrichr-0.0.6.dist-info/LICENSE
enrichr-0.0.6.dist-info/METADATA
enrichr-0.0.6.dist-info/WHEEL
enrichr-0.0.6.dist-info/top_level.txt
enrichr-0.0.6.dist-info/RECORD
