Metadata-Version: 2.1
Name: enrichr
Version: 0.0.6
Summary: Security Enrichment Framework
Home-page: https://github.com/jpleger/enrichr
Author: James Pleger
Author-email: jpleger@gmail.com
License: UNKNOWN
Platform: UNKNOWN
Classifier: Programming Language :: Python :: 3
Classifier: License :: OSI Approved :: GNU Affero General Public License v3 or later (AGPLv3+)
Classifier: Operating System :: OS Independent
Classifier: Development Status :: 1 - Planning
Classifier: Topic :: Software Development :: Libraries :: Application Frameworks
Requires-Python: >=3.6
Requires-Dist: requests (>=2.25.1)
